.gitignore
.readthedocs.yml
CHANGELOG.md
LICENSE
README.md
environment.yml
requirements.txt
setup.py
docs/Makefile
docs/cli.rst
docs/conf.py
docs/environment.yml
docs/index.rst
docs/installation.rst
docs/intro.rst
docs/make.bat
docs/notebooks.rst
docs/requirements.txt
docs/api/index.rst
docs/img/ODM_point_cloud.gif
examples/GS__2098.JPG
examples/forest.mp4
notebooks/README.rst
notebooks/geotags.ipynb
notebooks/odmax_webodm.ipynb
notebooks/odmax_webodm_OAuth.ipynb
notebooks/reprojection.ipynb
odmax/__init__.py
odmax/api.py
odmax/cli.py
odmax/consts.py
odmax/exif.py
odmax/gpx.fmt
odmax/helpers.py
odmax/io.py
odmax/process.py
odmax/py360.py
odmax/utils.py
odmax.egg-info/PKG-INFO
odmax.egg-info/SOURCES.txt
odmax.egg-info/dependency_links.txt
odmax.egg-info/entry_points.txt
odmax.egg-info/not-zip-safe
odmax.egg-info/requires.txt
odmax.egg-info/top_level.txt