Metadata-Version: 2.1
Name: odmax
Version: 0.1.1
Summary: odmax extracts still images from GoPro 360 camera types, including GNSS location and time information
Home-page: https://github.com/localdevices/ODMax
Author: Hessel Winsemius and Stephen Mather
Author-email: info@rainbowsensing.com
License: AGPLv3
Keywords: GoPro,OpenDroneMap
Platform: UNKNOWN
Classifier: Development Status :: 5 - Production/Stable
Classifier: Intended Audience :: Developers
Classifier: Intended Audience :: Education
Classifier: Intended Audience :: Science/Research
Classifier: Topic :: Scientific/Engineering :: GIS
Classifier: License :: OSI Approved :: GNU Affero General Public License v3
Classifier: Programming Language :: Python :: 3
Classifier: Programming Language :: Python :: 3.8
Classifier: Programming Language :: Python :: 3.9
Requires-Python: >=3.8
Provides-Extra: dev
Provides-Extra: optional
License-File: LICENSE
